physrisk_api/__init__.py
physrisk_api/app/__init__.py
physrisk_api/app/api.py
physrisk_api/app/service.py
physrisk_api-0.0.3.dist-info/LICENSE
physrisk_api-0.0.3.dist-info/METADATA
physrisk_api-0.0.3.dist-info/WHEEL
physrisk_api-0.0.3.dist-info/top_level.txt
physrisk_api-0.0.3.dist-info/RECORD
